{
	"block": {
		"image": {
			"id": "id-1-2-3",
			"_v": 0
		}
	},
	"block": {
		"image": {
			"id": "id-1-2-3",
			"_v": 0
		}
	},
	"block": {
		"image": {
			"id": "id-1-2-3",
			"_v": 0
		}
	},
	"block": {
		"image": {
			"id": "id-1-2-3",
			"_v": 0
		}
	},
	"block": {
		"image": {
			"id": "id-1-2-3",
			"_v": 0
		}
	}
}



// Нужно выбрать способ создавать последовательные уник ид
// для костантного поиска по дереву
// после разработать метод диффа
// {
// 	type: "BLOCK",
// 	data...
// 	childs: {
// 		"id-w-1-2-3": {
// 			type: WIDGET
// 		}
// 	}
// }